{"sections":{"main":{"type":"main-page","disabled":true,"settings":{"padding_top":28,"padding_bottom":28}},"rich_text_edHJVb":{"type":"rich-text","blocks":{"heading_Tc3V8J":{"type":"heading","settings":{"heading":"Maxfoot Payment Plan","heading_size":"h1"}},"text_gdTg3L":{"type":"text","settings":{"text":"<h3>We offer payment via Shop Pay. You can choose the plan to get your bike first and pay later.<\/h3>"}}},"block_order":["heading_Tc3V8J","text_gdTg3L"],"custom_css":["{margin-bottom: -50px;}"],"settings":{"desktop_content_position":"center","content_alignment":"center","color_scheme":"background-1","full_width":true,"padding_top":40,"padding_bottom":52}},"multirow_QWRaMx":{"type":"multirow","blocks":{"row_abP7fK":{"type":"row","settings":{"image":"shopify:\/\/shop_images\/2_7448f356-a469-46e7-a7c9-6ca1eb693637.png","caption":"","heading":"Find Plans on Product Page","text":"","button_label":"","button_link":""}},"row_fN8HyX":{"type":"row","settings":{"image":"shopify:\/\/shop_images\/6_c01ae3aa-ebdf-4012-be08-e3691d98e332.png","caption":"","heading":"Check Your Payment Plan","text":"","button_label":"","button_link":""}},"row_J7EgPB":{"type":"row","settings":{"image":"shopify:\/\/shop_images\/1_7c63d649-dce6-4c3a-90c7-0146306cc93a.png","caption":"","heading":"Select on Checkout Page","text":"","button_label":"","button_link":""}}},"block_order":["row_abP7fK","row_fN8HyX","row_J7EgPB"],"settings":{"image_height":"adapt","desktop_image_width":"medium","heading_size":"h1","text_style":"body","button_style":"secondary","desktop_content_position":"middle","desktop_content_alignment":"left","image_layout":"align-left","section_color_scheme":"background-1","row_color_scheme":"background-1","mobile_content_alignment":"left","padding_top":36,"padding_bottom":36}}},"order":["main","rich_text_edHJVb","multirow_QWRaMx"]}